modfname/__init__.py
modfname/modfname.py
modfname-1.1.5.dist-info/LICENSE
modfname-1.1.5.dist-info/METADATA
modfname-1.1.5.dist-info/WHEEL
modfname-1.1.5.dist-info/entry_points.txt
modfname-1.1.5.dist-info/top_level.txt
modfname-1.1.5.dist-info/RECORD
