Metadata-Version: 2.1
Name: modfname
Version: 1.1.5
Summary: File and folder CLI name modifier on the all system
Home-page: https://github.com/yoarch/modfname
Author: yoarch
Author-email: yo.managements@gmail.com
License: UNKNOWN
Platform: UNKNOWN
Classifier: Programming Language :: Python :: 3
Classifier: License :: OSI Approved :: MIT License
Classifier: Operating System :: OS Independent
Requires-Python: >=3
